{
    "backend": "django",
    "db_name": "",
    "db_pass": "",
    "db_type": "sqlite",
    "db_user": "",
    "dbms": "1",
    "description": "generated product",
    "design": "volt-dashboard",
    "docker": "1",
    "err_code": 0,
    "frontend": "",
    "heroku": "0",
    "pattern": "mvc",
    "pro": "0",
    "task_id": "3e579378-14d9-48aa-ae2f-13005165505b",
    "task_info": "Upload Sources [0%] - 491 files",
    "task_output": "3e579378-14d9-48aa-ae2f-13005165505b.zip",
    "task_result": "SUCCESS",
    "task_state": "RUNNING",
    "task_ts_end": "2023-10-24-16-27-19",
    "task_ts_start": "2023-10-24-16-27-17"
}